index.py
plover_undo_tools-0.0.0.dist-info/METADATA
plover_undo_tools-0.0.0.dist-info/WHEEL
plover_undo_tools-0.0.0.dist-info/entry_points.txt
plover_undo_tools-0.0.0.dist-info/top_level.txt
plover_undo_tools-0.0.0.dist-info/zip-safe
plover_undo_tools-0.0.0.dist-info/RECORD
