Metadata-Version: 2.1
Name: plover-undo-tools
Version: 0.0.0
Summary: Customize the undo behavior of certain entries
Keywords: plover plover_plugin
Classifier: Environment :: Plugins
Classifier: Intended Audience :: End Users/Desktop
Classifier: Programming Language :: Python :: 3
Classifier: Programming Language :: Python :: 3.10
Requires-Dist: plover >=4.0.0rc2
